odoo9_addon_purchase_analytic_global-9.0.1.0.0-nspkg.pth
odoo_addons/purchase_analytic_global/README.rst
odoo_addons/purchase_analytic_global/__init__.py
odoo_addons/purchase_analytic_global/__openerp__.py
odoo_addons/purchase_analytic_global/i18n/fr.po
odoo_addons/purchase_analytic_global/i18n/purchase_analytic_global.pot
odoo_addons/purchase_analytic_global/models/__init__.py
odoo_addons/purchase_analytic_global/models/purchase.py
odoo_addons/purchase_analytic_global/static/description/icon.png
odoo_addons/purchase_analytic_global/views/purchase.xml
odoo9_addon_purchase_analytic_global-9.0.1.0.0.dist-info/METADATA
odoo9_addon_purchase_analytic_global-9.0.1.0.0.dist-info/WHEEL
odoo9_addon_purchase_analytic_global-9.0.1.0.0.dist-info/namespace_packages.txt
odoo9_addon_purchase_analytic_global-9.0.1.0.0.dist-info/top_level.txt
odoo9_addon_purchase_analytic_global-9.0.1.0.0.dist-info/RECORD
